jasonite/__init__.py
jasonite/core.py
jasonite-0.1.4.dist-info/licenses/LICENSE
jasonite-0.1.4.dist-info/METADATA
jasonite-0.1.4.dist-info/WHEEL
jasonite-0.1.4.dist-info/top_level.txt
jasonite-0.1.4.dist-info/RECORD
