Metadata-Version: 2.4
Name: jasonite
Version: 0.1.4
Summary: Jasonite: a tiny JSON-backed document store for Python
Home-page: https://github.com/guelfoweb/jasonite
Author: Gianni Amato
Author-email: guelfoweb@gmail.com
Classifier: Programming Language :: Python :: 3
Classifier: License :: OSI Approved :: MIT License
Classifier: Operating System :: OS Independent
Classifier: Topic :: Database
Classifier: Topic :: Software Development :: Libraries :: Python Modules
Requires-Python: >=3.8
License-File: LICENSE
Dynamic: author
Dynamic: author-email
Dynamic: classifier
Dynamic: home-page
Dynamic: license-file
Dynamic: requires-python
Dynamic: summary
